README.rst
setup.py
lit_utest/__init__.py
lit_utest.egg-info/PKG-INFO
lit_utest.egg-info/SOURCES.txt
lit_utest.egg-info/dependency_links.txt
lit_utest.egg-info/top_level.txt