Metadata-Version: 1.1
Name: lit-utest
Version: 0.1.0
Summary: llvm-lit module for first-class utest.h unit test support
Home-page: https://github.com/ldrumm/lit_utest
Author: ldrumm
Author-email: ldrumm@rtps.co
License: MIT
Platform: UNKNOWN
Classifier: Development Status :: 2 - Pre-Alpha
Classifier: License :: Public Domain
Classifier: Programming Language :: Python
Classifier: Programming Language :: Python :: 2
Classifier: Programming Language :: Python :: 2.7
Classifier: Programming Language :: Python :: 3
Classifier: Programming Language :: Python :: 3.4
Classifier: Programming Language :: Python :: 3.5
Classifier: Programming Language :: Python :: 3.6
Classifier: Programming Language :: Python :: 3.7
